LICENSE.txt
README.md
setup.py
edimez14_password_generator_1.egg-info/PKG-INFO
edimez14_password_generator_1.egg-info/SOURCES.txt
edimez14_password_generator_1.egg-info/dependency_links.txt
edimez14_password_generator_1.egg-info/entry_points.txt
edimez14_password_generator_1.egg-info/top_level.txt
password_generator/__init__.py
password_generator/password_generator.py