Metadata-Version: 2.1
Name: edimez14-password-generator-1
Version: 0.4
Summary: password generator
Home-page: https://github.com/edimez14/password_generator
Author: edizon
Author-email: edimez14@gmail.com
License: UNKNOWN
Platform: UNKNOWN
Classifier: Programming Language :: Python :: 3
Classifier: License :: OSI Approved :: Apache Software License
Classifier: Operating System :: OS Independent
Requires-Python: >=3.6
License-File: LICENSE.txt
